{
  "id": "event_1752415892505_zlvya2q0w",
  "version": "1.0",
  "event": {
    "name": "Lost Turkey Trail Races",
    "date": "2025-07-26",
    "location": "Imler, PA",
    "description": "Welcome to Central Pennsylvania's ridges and valleys! 50K point-to-point, Half-Marathon loop, and 10K Little Turkey races."
  },
  "aidStations": [
    {
      "id": "start",
      "name": "Start",
      "isDefault": true
    },
    {
      "id": "dnf",
      "name": "DNF",
      "isDefault": true
    },
    {
      "id": "dns",
      "name": "DNS",
      "isDefault": true
    },
    {
      "id": "skyline",
      "name": "Skyline Drive",
      "isDefault": false
    },
    {
      "id": "burnt-house",
      "name": "Burnt House",
      "isDefault": false
    },
    {
      "id": "lost-children",
      "name": "Lost Children",
      "isDefault": false
    },
    {
      "id": "hairpin",
      "name": "Hairpin",
      "isDefault": false
    }
  ],
  "courses": [
    {
      "id": "50k",
      "name": "50K",
      "stations": [
        {
          "stationId": "start",
          "distance": 0,
          "cumulative": 0,
          "cumulativeDistance": 0
        },
        {
          "stationId": "skyline",
          "distance": 8.6,
          "cumulative": 8.6,
          "cumulativeDistance": 8.6
        },
        {
          "stationId": "burnt-house",
          "distance": 8.3,
          "cumulative": 16.9,
          "cumulativeDistance": 16.9
        },
        {
          "stationId": "lost-children",
          "distance": 6.6,
          "cumulative": 23.9,
          "cumulativeDistance": 23.9
        },
        {
          "stationId": "hairpin",
          "distance": 3.5,
          "cumulative": 27,
          "cumulativeDistance": 27
        }
      ],
      "totalDistance": 31
    },
    {
      "id": "half-marathon",
      "name": "Half-Marathon",
      "stations": [
        {
          "stationId": "start",
          "distance": 0,
          "cumulative": 0,
          "cumulativeDistance": 0
        },
        {
          "stationId": "lost-children",
          "distance": 5.7,
          "cumulative": 5.7,
          "cumulativeDistance": 5.7
        },
        {
          "stationId": "hairpin",
          "distance": 3.5,
          "cumulative": 9.2,
          "cumulativeDistance": 9.2
        }
      ],
      "totalDistance": 13.2
    }
  ],
  "participants": [
    {
      "id": "100",
      "name": "100",
      "type": "race",
      "active": true,
      "courseId": "50k"
    },
    {
      "id": "101",
      "name": "101",
      "type": "race",
      "active": true,
      "courseId": "50k"
    },
    {
      "id": "102",
      "name": "102",
      "type": "race",
      "active": true,
      "courseId": "50k"
    },
    {
      "id": "103",
      "name": "103",
      "type": "race",
      "active": true,
      "courseId": "50k"
    },
    {
      "id": "104",
      "name": "104",
      "type": "race",
      "active": true,
      "courseId": "50k"
    },
    {
      "id": "105",
      "name": "105",
      "type": "race",
      "active": true,
      "courseId": "50k"
    },
    {
      "id": "106",
      "name": "106",
      "type": "race",
      "active": true,
      "courseId": "50k"
    },
    {
      "id": "107",
      "name": "107",
      "type": "race",
      "active": true,
      "courseId": "50k"
    },
    {
      "id": "108",
      "name": "108",
      "type": "race",
      "active": true,
      "courseId": "50k"
    },
    {
      "id": "109",
      "name": "109",
      "type": "race",
      "active": true,
      "courseId": "50k"
    },
    {
      "id": "110",
      "name": "110",
      "type": "race",
      "active": true,
      "courseId": "50k"
    },
    {
      "id": "111",
      "name": "111",
      "type": "race",
      "active": true,
      "courseId": "50k"
    },
    {
      "id": "112",
      "name": "112",
      "type": "race",
      "active": true,
      "courseId": "50k"
    },
    {
      "id": "113",
      "name": "113",
      "type": "race",
      "active": true,
      "courseId": "50k"
    },
    {
      "id": "114",
      "name": "114",
      "type": "race",
      "active": true,
      "courseId": "50k"
    },
    {
      "id": "115",
      "name": "115",
      "type": "race",
      "active": true,
      "courseId": "50k"
    },
    {
      "id": "116",
      "name": "116",
      "type": "race",
      "active": true,
      "courseId": "50k"
    },
    {
      "id": "117",
      "name": "117",
      "type": "race",
      "active": true,
      "courseId": "50k"
    },
    {
      "id": "118",
      "name": "118",
      "type": "race",
      "active": true,
      "courseId": "50k"
    },
    {
      "id": "119",
      "name": "119",
      "type": "race",
      "active": true,
      "courseId": "50k"
    },
    {
      "id": "120",
      "name": "120",
      "type": "race",
      "active": true,
      "courseId": "50k"
    },
    {
      "id": "300",
      "name": "300",
      "type": "race",
      "active": true,
      "courseId": "half-marathon"
    },
    {
      "id": "301",
      "name": "301",
      "type": "race",
      "active": true,
      "courseId": "half-marathon"
    },
    {
      "id": "302",
      "name": "302",
      "type": "race",
      "active": true,
      "courseId": "half-marathon"
    },
    {
      "id": "303",
      "name": "303",
      "type": "race",
      "active": true,
      "courseId": "half-marathon"
    },
    {
      "id": "304",
      "name": "304",
      "type": "race",
      "active": true,
      "courseId": "half-marathon"
    },
    {
      "id": "305",
      "name": "305",
      "type": "race",
      "active": true,
      "courseId": "half-marathon"
    },
    {
      "id": "306",
      "name": "306",
      "type": "race",
      "active": true,
      "courseId": "half-marathon"
    },
    {
      "id": "307",
      "name": "307",
      "type": "race",
      "active": true,
      "courseId": "half-marathon"
    },
    {
      "id": "308",
      "name": "308",
      "type": "race",
      "active": true,
      "courseId": "half-marathon"
    },
    {
      "id": "309",
      "name": "309",
      "type": "race",
      "active": true,
      "courseId": "half-marathon"
    },
    {
      "id": "310",
      "name": "310",
      "type": "race",
      "active": true,
      "courseId": "half-marathon"
    },
    {
      "id": "311",
      "name": "311",
      "type": "race",
      "active": true,
      "courseId": "half-marathon"
    },
    {
      "id": "312",
      "name": "312",
      "type": "race",
      "active": true,
      "courseId": "half-marathon"
    },
    {
      "id": "313",
      "name": "313",
      "type": "race",
      "active": true,
      "courseId": "half-marathon"
    },
    {
      "id": "314",
      "name": "314",
      "type": "race",
      "active": true,
      "courseId": "half-marathon"
    },
    {
      "id": "315",
      "name": "315",
      "type": "race",
      "active": true,
      "courseId": "half-marathon"
    },
    {
      "id": "316",
      "name": "316",
      "type": "race",
      "active": true,
      "courseId": "half-marathon"
    },
    {
      "id": "317",
      "name": "317",
      "type": "race",
      "active": true,
      "courseId": "half-marathon"
    },
    {
      "id": "318",
      "name": "318",
      "type": "race",
      "active": true,
      "courseId": "half-marathon"
    },
    {
      "id": "319",
      "name": "319",
      "type": "race",
      "active": true,
      "courseId": "half-marathon"
    },
    {
      "id": "320",
      "name": "320",
      "type": "race",
      "active": true,
      "courseId": "half-marathon"
    },
    {
      "id": "321",
      "name": "321",
      "type": "race",
      "active": true,
      "courseId": "half-marathon"
    },
    {
      "id": "322",
      "name": "322",
      "type": "race",
      "active": true,
      "courseId": "half-marathon"
    },
    {
      "id": "323",
      "name": "323",
      "type": "race",
      "active": true,
      "courseId": "half-marathon"
    },
    {
      "id": "324",
      "name": "324",
      "type": "race",
      "active": true,
      "courseId": "half-marathon"
    },
    {
      "id": "325",
      "name": "325",
      "type": "race",
      "active": true,
      "courseId": "half-marathon"
    },
    {
      "id": "326",
      "name": "326",
      "type": "race",
      "active": true,
      "courseId": "half-marathon"
    },
    {
      "id": "327",
      "name": "327",
      "type": "race",
      "active": true,
      "courseId": "half-marathon"
    },
    {
      "id": "328",
      "name": "328",
      "type": "race",
      "active": true,
      "courseId": "half-marathon"
    },
    {
      "id": "329",
      "name": "329",
      "type": "race",
      "active": true,
      "courseId": "half-marathon"
    },
    {
      "id": "330",
      "name": "330",
      "type": "race",
      "active": true,
      "courseId": "half-marathon"
    },
    {
      "id": "331",
      "name": "331",
      "type": "race",
      "active": true,
      "courseId": "half-marathon"
    },
    {
      "id": "332",
      "name": "332",
      "type": "race",
      "active": true,
      "courseId": "half-marathon"
    },
    {
      "id": "333",
      "name": "333",
      "type": "race",
      "active": true,
      "courseId": "half-marathon"
    },
    {
      "id": "334",
      "name": "334",
      "type": "race",
      "active": true,
      "courseId": "half-marathon"
    },
    {
      "id": "335",
      "name": "335",
      "type": "race",
      "active": true,
      "courseId": "half-marathon"
    },
    {
      "id": "336",
      "name": "336",
      "type": "race",
      "active": true,
      "courseId": "half-marathon"
    },
    {
      "id": "337",
      "name": "337",
      "type": "race",
      "active": true,
      "courseId": "half-marathon"
    },
    {
      "id": "338",
      "name": "338",
      "type": "race",
      "active": true,
      "courseId": "half-marathon"
    },
    {
      "id": "339",
      "name": "339",
      "type": "race",
      "active": true,
      "courseId": "half-marathon"
    },
    {
      "id": "340",
      "name": "340",
      "type": "race",
      "active": true,
      "courseId": "half-marathon"
    },
    {
      "id": "341",
      "name": "341",
      "type": "race",
      "active": true,
      "courseId": "half-marathon"
    },
    {
      "id": "342",
      "name": "342",
      "type": "race",
      "active": true,
      "courseId": "half-marathon"
    },
    {
      "id": "343",
      "name": "343",
      "type": "race",
      "active": true,
      "courseId": "half-marathon"
    },
    {
      "id": "344",
      "name": "344",
      "type": "race",
      "active": true,
      "courseId": "half-marathon"
    },
    {
      "id": "345",
      "name": "345",
      "type": "race",
      "active": true,
      "courseId": "half-marathon"
    },
    {
      "id": "346",
      "name": "346",
      "type": "race",
      "active": true,
      "courseId": "half-marathon"
    },
    {
      "id": "347",
      "name": "347",
      "type": "race",
      "active": true,
      "courseId": "half-marathon"
    },
    {
      "id": "348",
      "name": "348",
      "type": "race",
      "active": true,
      "courseId": "half-marathon"
    },
    {
      "id": "349",
      "name": "349",
      "type": "race",
      "active": true,
      "courseId": "half-marathon"
    },
    {
      "id": "350",
      "name": "350",
      "type": "race",
      "active": true,
      "courseId": "half-marathon"
    },
    {
      "id": "121",
      "name": "121",
      "type": "race",
      "active": true,
      "courseId": "50k"
    },
    {
      "id": "122",
      "name": "122",
      "type": "race",
      "active": true,
      "courseId": "50k"
    },
    {
      "id": "123",
      "name": "123",
      "type": "race",
      "active": true,
      "courseId": "50k"
    },
    {
      "id": "124",
      "name": "124",
      "type": "race",
      "active": true,
      "courseId": "50k"
    },
    {
      "id": "125",
      "name": "125",
      "type": "race",
      "active": true,
      "courseId": "50k"
    },
    {
      "id": "126",
      "name": "126",
      "type": "race",
      "active": true,
      "courseId": "50k"
    },
    {
      "id": "127",
      "name": "127",
      "type": "race",
      "active": true,
      "courseId": "50k"
    },
    {
      "id": "128",
      "name": "128",
      "type": "race",
      "active": true,
      "courseId": "50k"
    },
    {
      "id": "129",
      "name": "129",
      "type": "race",
      "active": true,
      "courseId": "50k"
    },
    {
      "id": "130",
      "name": "130",
      "type": "race",
      "active": true,
      "courseId": "50k"
    },
    {
      "id": "131",
      "name": "131",
      "type": "race",
      "active": true,
      "courseId": "50k"
    },
    {
      "id": "132",
      "name": "132",
      "type": "race",
      "active": true,
      "courseId": "50k"
    },
    {
      "id": "133",
      "name": "133",
      "type": "race",
      "active": true,
      "courseId": "50k"
    },
    {
      "id": "134",
      "name": "134",
      "type": "race",
      "active": true,
      "courseId": "50k"
    },
    {
      "id": "135",
      "name": "135",
      "type": "race",
      "active": true,
      "courseId": "50k"
    },
    {
      "id": "136",
      "name": "136",
      "type": "race",
      "active": true,
      "courseId": "50k"
    },
    {
      "id": "137",
      "name": "137",
      "type": "race",
      "active": true,
      "courseId": "50k"
    },
    {
      "id": "138",
      "name": "138",
      "type": "race",
      "active": true,
      "courseId": "50k"
    },
    {
      "id": "139",
      "name": "139",
      "type": "race",
      "active": true,
      "courseId": "50k"
    },
    {
      "id": "140",
      "name": "140",
      "type": "race",
      "active": true,
      "courseId": "50k"
    },
    {
      "id": "141",
      "name": "141",
      "type": "race",
      "active": true,
      "courseId": "50k"
    },
    {
      "id": "142",
      "name": "142",
      "type": "race",
      "active": true,
      "courseId": "50k"
    },
    {
      "id": "143",
      "name": "143",
      "type": "race",
      "active": true,
      "courseId": "50k"
    },
    {
      "id": "144",
      "name": "144",
      "type": "race",
      "active": true,
      "courseId": "50k"
    },
    {
      "id": "145",
      "name": "145",
      "type": "race",
      "active": true,
      "courseId": "50k"
    },
    {
      "id": "146",
      "name": "146",
      "type": "race",
      "active": true,
      "courseId": "50k"
    },
    {
      "id": "147",
      "name": "147",
      "type": "race",
      "active": true,
      "courseId": "50k"
    },
    {
      "id": "148",
      "name": "148",
      "type": "race",
      "active": true,
      "courseId": "50k"
    },
    {
      "id": "149",
      "name": "149",
      "type": "race",
      "active": true,
      "courseId": "50k"
    },
    {
      "id": "150",
      "name": "150",
      "type": "race",
      "active": true,
      "courseId": "50k"
    }
  ],
  "stationAssignments": {
    "start": [
      "100",
      "101",
      "103",
      "104",
      "105",
      "106",
      "107",
      "108",
      "109",
      "110",
      "111",
      "112",
      "113",
      "114",
      "115",
      "116",
      "117",
      "118",
      "119",
      "120",
      "300",
      "301",
      "302",
      "303",
      "304",
      "305",
      "306",
      "307",
      "308",
      "309",
      "310",
      "311",
      "312",
      "313",
      "314",
      "315",
      "316",
      "317",
      "318",
      "319",
      "320",
      "321",
      "322",
      "323",
      "324",
      "325",
      "326",
      "327",
      "328",
      "329",
      "330",
      "331",
      "332",
      "333",
      "334",
      "335",
      "336",
      "337",
      "338",
      "339",
      "340",
      "341",
      "342",
      "343",
      "344",
      "345",
      "346",
      "347",
      "348",
      "349",
      "350",
      "121",
      "122",
      "123",
      "124",
      "125",
      "126",
      "127",
      "128",
      "129",
      "130",
      "131",
      "132",
      "133",
      "134",
      "135",
      "136",
      "137",
      "138",
      "139",
      "140",
      "141",
      "142",
      "143",
      "144",
      "145",
      "146",
      "147",
      "148",
      "149",
      "150"
    ]
  },
  "activityLog": [],
  "exportedAt": "2025-07-13T14:13:00.168Z"
}